snirzoom/__init__.py
snirzoom/icon.ico
snirzoom-0.2.6.dist-info/METADATA
snirzoom-0.2.6.dist-info/WHEEL
snirzoom-0.2.6.dist-info/top_level.txt
snirzoom-0.2.6.dist-info/RECORD
