Metadata-Version: 2.1
Name: snirzoom
Version: 0.2.6
Summary: automate zoom meeting
Home-page: UNKNOWN
Author: snir dekel
Author-email: snirdekel101@gmail.com
License: MIT
Keywords: zoom
Platform: UNKNOWN
Classifier: Development Status :: 5 - Production/Stable
Classifier: Intended Audience :: Education
Classifier: Operating System :: Microsoft :: Windows :: Windows 10
Classifier: License :: OSI Approved :: MIT License
Classifier: Programming Language :: Python :: 3
Requires-Dist: ttkthemes
Requires-Dist: pyperclip
